dicebear/__init__.py
dicebear/avatar.py
dicebear/errors.py
dicebear/metadata.py
dicebear/models.py
dicebear/utility.py
dicebear-3.9.4.dist-info/licenses/LICENSE
dicebear-3.9.4.dist-info/METADATA
dicebear-3.9.4.dist-info/WHEEL
dicebear-3.9.4.dist-info/top_level.txt
dicebear-3.9.4.dist-info/RECORD
