Metadata-Version: 2.4
Name: dicebear
Version: 3.9.4
Summary: A python wrapper for DiceBear's avatar generating API.
Home-page: https://dicebear.vhjan.me/
Author: jvherck
Author-email: jan@vhjan.me
Maintainer: jvherck
Maintainer-email: jan@vhjan.me
License: MIT License
Project-URL: Documentation, https://dicebear.vhjan.me/
Project-URL: Source, https://github.com/jvherck/dicebear
Project-URL: Tracker, https://github.com/jvherck/dicebear/issues
Keywords: python,dicebear,avatar,avatars,generating,generation,generator,API,wrapper,image,images,picture,pictures,png,jpg,svg,json,cli,pillow,pil,requests,adventurer,adventurer-neutral,avataaars,avataaars-neutral,big-ears,big-ears-neutral,big-smile,bottts,bottts-neutral,croodles,croodles-neutral,fun-emoji,icons,identicon,initials,lorelei,lorelei-neutral,micah,miniavs,notionists,notionists-neutral,open-peeps,personas,pixel-art,pixel-art-neutral,shapes,thumbs,toon-head
Classifier: Development Status :: 5 - Production/Stable
Classifier: Intended Audience :: Developers
Classifier: Intended Audience :: Other Audience
Classifier: Natural Language :: English
Classifier: Programming Language :: Python :: 3
Classifier: Programming Language :: Python :: 3 :: Only
Classifier: Programming Language :: Python :: 3.7
Classifier: Programming Language :: Python :: 3.8
Classifier: Programming Language :: Python :: 3.9
Classifier: Programming Language :: Python :: 3.10
Classifier: Programming Language :: Python :: 3.11
Classifier: Programming Language :: Python :: 3.12
Classifier: Programming Language :: Python :: 3.13
Classifier: Programming Language :: Python :: 3.14
Classifier: Operating System :: Unix
Classifier: Operating System :: MacOS
Classifier: Operating System :: Microsoft :: Windows
Classifier: License :: OSI Approved :: MIT License
Classifier: Topic :: Artistic Software
Classifier: Topic :: Games/Entertainment
Classifier: Topic :: Multimedia :: Graphics
Classifier: Topic :: Other/Nonlisted Topic
Classifier: Topic :: Software Development :: Libraries :: Python Modules
Requires-Python: >=3.7
License-File: LICENSE
Requires-Dist: requests
Requires-Dist: urllib3
Dynamic: author
Dynamic: author-email
Dynamic: classifier
Dynamic: description
Dynamic: description-content-type
Dynamic: home-page
Dynamic: keywords
Dynamic: license
Dynamic: license-file
Dynamic: maintainer
Dynamic: maintainer-email
Dynamic: project-url
Dynamic: requires-dist
Dynamic: requires-python
Dynamic: summary
